colout/__init__.py
colout/colout.py
colout/colout_clang.py
colout/colout_cmake.py
colout/colout_configure.py
colout/colout_ctest.py
colout/colout_g++.py
colout/colout_javac.py
colout/colout_json.py
colout/colout_latex.py
colout/colout_ninja.py
colout/colout_perm.py
colout/colout_python.py
colout/colout_valgrind.py
colout_fix-0.6.1.data/scripts/colout
colout_fix-0.6.1.dist-info/LICENSE
colout_fix-0.6.1.dist-info/METADATA
colout_fix-0.6.1.dist-info/WHEEL
colout_fix-0.6.1.dist-info/top_level.txt
colout_fix-0.6.1.dist-info/RECORD
