Metadata-Version: 2.1
Name: colout-fix
Version: 0.6.1
Summary: Color Up Arbitrary Command Output.
Home-page: http://nojhan.github.com/colout/
Author: nojhan
Author-email: nojhan@nojhan.net
License: GPLv3
Platform: UNKNOWN
Requires-Dist: pygments
Requires-Dist: babel
Requires-Dist: argparse; python_version < "2.7"
